[{"timestamp":1648306501477,"files":[{"filename":"bundle.*****.esm.js","previous":73088,"size":73064,"diff":-24},{"filename":"polyfills.*****.esm.js","previous":2180,"size":2180,"diff":0},{"filename":"polyfills.d6cf1.js","previous":2279,"size":2279,"diff":0},{"filename":"index.html","previous":1212,"size":1211,"diff":-1},{"filename":"bundle.c3bc7.css","previous":25355,"size":0,"diff":-25355},{"filename":"bundle.970f4.js","previous":77756,"size":0,"diff":-77756},{"filename":"bundle.5ad6d.css","previous":0,"size":25290,"diff":25290},{"filename":"bundle.d1d8e.js","previous":0,"size":77694,"diff":77694}]},{"timestamp":1648304874256,"files":[{"filename":"bundle.*****.esm.js","previous":73145,"size":73088,"diff":-57},{"filename":"polyfills.*****.esm.js","previous":2180,"size":2180,"diff":0},{"filename":"sw.js","previous":10530,"size":0,"diff":-10530},{"filename":"sw-esm.js","previous":10535,"size":0,"diff":-10535},{"filename":"polyfills.d6cf1.js","previous":2279,"size":2279,"diff":0},{"filename":"index.html","previous":1210,"size":1212,"diff":2},{"filename":"200.html","previous":1210,"size":0,"diff":-1210},{"filename":"bundle.c3bc7.css","previous":25355,"size":25355,"diff":0},{"filename":"bundle.ba121.js","previous":77808,"size":0,"diff":-77808},{"filename":"bundle.970f4.js","previous":0,"size":77756,"diff":77756}]},{"timestamp":1648303677922,"files":[{"filename":"bundle.*****.esm.js","previous":73140,"size":73145,"diff":5},{"filename":"polyfills.*****.esm.js","previous":2180,"size":2180,"diff":0},{"filename":"sw.js","previous":10534,"size":10530,"diff":-4},{"filename":"sw-esm.js","previous":10539,"size":10535,"diff":-4},{"filename":"polyfills.d6cf1.js","previous":2279,"size":2279,"diff":0},{"filename":"index.html","previous":1212,"size":1210,"diff":-2},{"filename":"200.html","previous":1212,"size":1210,"diff":-2},{"filename":"bundle.c3bc7.css","previous":25355,"size":25355,"diff":0},{"filename":"bundle.b20c7.js","previous":77801,"size":0,"diff":-77801},{"filename":"bundle.ba121.js","previous":0,"size":77808,"diff":77808}]},{"timestamp":1648302354827,"files":[{"filename":"bundle.*****.esm.js","previous":64241,"size":73140,"diff":8899},{"filename":"polyfills.*****.esm.js","previous":2180,"size":2180,"diff":0},{"filename":"sw.js","previous":10533,"size":10534,"diff":1},{"filename":"sw-esm.js","previous":10536,"size":10539,"diff":3},{"filename":"polyfills.d6cf1.js","previous":2279,"size":2279,"diff":0},{"filename":"index.html","previous":1211,"size":1212,"diff":1},{"filename":"200.html","previous":1211,"size":1212,"diff":1},{"filename":"bundle.c3bc7.css","previous":25355,"size":25355,"diff":0},{"filename":"bundle.e82db.js","previous":67439,"size":0,"diff":-67439},{"filename":"bundle.b20c7.js","previous":0,"size":77801,"diff":77801}]},{"timestamp":1648301335822,"files":[{"filename":"bundle.5a58d.css","previous":454,"size":0,"diff":-454},{"filename":"bundle.*****.esm.js","previous":8374,"size":64241,"diff":55867},{"filename":"polyfills.*****.esm.js","previous":2180,"size":2180,"diff":0},{"filename":"route-home.chunk.8aeee.css","previous":74,"size":0,"diff":-74},{"filename":"route-home.chunk.*****.esm.js","previous":253,"size":0,"diff":-253},{"filename":"route-notfound.chunk.c2e10.css","previous":65,"size":0,"diff":-65},{"filename":"route-notfound.chunk.*****.esm.js","previous":299,"size":0,"diff":-299},{"filename":"route-profile.chunk.141aa.css","previous":77,"size":0,"diff":-77},{"filename":"route-profile.chunk.*****.esm.js","previous":1125,"size":0,"diff":-1125},{"filename":"sw.js","previous":10757,"size":10533,"diff":-224},{"filename":"sw-esm.js","previous":10756,"size":10536,"diff":-220},{"filename":"bundle.31586.js","previous":8416,"size":0,"diff":-8416},{"filename":"polyfills.d6cf1.js","previous":2279,"size":2279,"diff":0},{"filename":"route-home.chunk.561a8.js","previous":256,"size":0,"diff":-256},{"filename":"route-notfound.chunk.3fad6.js","previous":298,"size":0,"diff":-298},{"filename":"route-profile.chunk.26975.js","previous":1612,"size":0,"diff":-1612},{"filename":"index.html","previous":1047,"size":1211,"diff":164},{"filename":"200.html","previous":645,"size":1211,"diff":566},{"filename":"bundle.c3bc7.css","previous":0,"size":25355,"diff":25355},{"filename":"bundle.e82db.js","previous":0,"size":67439,"diff":67439}]},{"timestamp":1647790871229,"files":[{"filename":"ssr-build/ssr-bundle.021c6.css","previous":609,"size":0,"diff":-609},{"filename":"ssr-build/ssr-bundle.js","previous":4626,"size":0,"diff":-4626},{"filename":"bundle.5a58d.css","previous":0,"size":454,"diff":454},{"filename":"bundle.*****.esm.js","previous":0,"size":8374,"diff":8374},{"filename":"polyfills.*****.esm.js","previous":0,"size":2180,"diff":2180},{"filename":"route-home.chunk.8aeee.css","previous":0,"size":74,"diff":74},{"filename":"route-home.chunk.*****.esm.js","previous":0,"size":253,"diff":253},{"filename":"route-notfound.chunk.c2e10.css","previous":0,"size":65,"diff":65},{"filename":"route-notfound.chunk.*****.esm.js","previous":0,"size":299,"diff":299},{"filename":"route-profile.chunk.141aa.css","previous":0,"size":77,"diff":77},{"filename":"route-profile.chunk.*****.esm.js","previous":0,"size":1125,"diff":1125},{"filename":"sw.js","previous":0,"size":10757,"diff":10757},{"filename":"sw-esm.js","previous":0,"size":10756,"diff":10756},{"filename":"bundle.31586.js","previous":0,"size":8416,"diff":8416},{"filename":"polyfills.d6cf1.js","previous":0,"size":2279,"diff":2279},{"filename":"route-home.chunk.561a8.js","previous":0,"size":256,"diff":256},{"filename":"route-notfound.chunk.3fad6.js","previous":0,"size":298,"diff":298},{"filename":"route-profile.chunk.26975.js","previous":0,"size":1612,"diff":1612},{"filename":"index.html","previous":0,"size":1047,"diff":1047},{"filename":"200.html","previous":0,"size":645,"diff":645}]}]
